ableton_set_builder/__init__.py
ableton_set_builder/ableton_set_builder.py
ableton_set_builder/templates/audio_track.xml
ableton_set_builder-0.1.0.dist-info/licenses/LICENCE
ableton_set_builder-0.1.0.dist-info/METADATA
ableton_set_builder-0.1.0.dist-info/WHEEL
ableton_set_builder-0.1.0.dist-info/top_level.txt
ableton_set_builder-0.1.0.dist-info/RECORD
