Metadata-Version: 2.4
Name: ableton_set_builder
Version: 0.1.0
Summary: A package to build Ableton Live sets programmatically.
Home-page: https://github.com/PCO-Ableton/ableton_set_builder
Author: Lars & Manuel
Author-email: me@manuelmol.nl
Classifier: Programming Language :: Python :: 3
Classifier: License :: OSI Approved :: MIT License
Classifier: Operating System :: OS Independent
Requires-Python: >=3.6
License-File: LICENCE
Requires-Dist: xmltodict
Dynamic: author
Dynamic: author-email
Dynamic: classifier
Dynamic: description
Dynamic: description-content-type
Dynamic: home-page
Dynamic: license-file
Dynamic: requires-dist
Dynamic: requires-python
Dynamic: summary
